nesrs-0.1.2.dist-info/METADATA
nesrs-0.1.2.dist-info/WHEEL
nesrs/__init__.py
nesrs/nesrs.abi3.so
nesrs-0.1.2.dist-info/RECORD
