Metadata-Version: 2.4
Name: nesrs
Version: 0.1.2
Classifier: Development Status :: 4 - Beta
Classifier: Intended Audience :: Developers
Classifier: License :: OSI Approved :: MIT License
Classifier: Programming Language :: Python :: 3
Classifier: Programming Language :: Python :: 3.8
Classifier: Programming Language :: Python :: 3.9
Classifier: Programming Language :: Python :: 3.10
Classifier: Programming Language :: Python :: 3.11
Classifier: Programming Language :: Python :: 3.12
Classifier: Programming Language :: Rust
Summary: NES (Nintendo Entertainment System) emulator written in Rust with Python bindings
Keywords: python,rust,emulation
Author-email: Stefan Jovanovic <s.jovanovic3107@gmail.com>
License: MIT
Requires-Python: >=3.8
Project-URL: Homepage, https://github.com/StefanJo3107/nesrs
Project-URL: Repository, https://github.com/StefanJo3107/nesrs
Project-URL: Issues, https://github.com/StefanJo3107/nesrs/issues
